{
    "name": "Lycan",
    "description": "In the dark of the night, Lycans will do whatever it takes to help their pack.\n　",
    "powers": [
        "tepids_origins:labels/dimensions/overworld",
        "tepids_origins:labels/archetypes/combat",
        "tepids_origins:origins/lycan/skills",
        "tepids_origins:origins/lycan/hunter",
        "tepids_origins:origins/lycan/nocturnalpredator",
        "tepids_origins:origins/lycan/kinship",
        "tepids_origins:origins/lycan/preyontheweak",
        "tepids_origins:origins/lycan/pounce"
    ],
    "icon": {
        "item": "tepids_origins:protector_of_a_kin"
    },
    "order": 4,
    "impact": 2,
    "loading_priority": 0
}